{ 
   "data":[ 
      { 
         "CustomerPhone":"(678) 597-7119",
         "CustomerFirstName":"Stephanie",
         "CustomerEmail":"ssledge@manh.com",
         "CustomerLastName":"Sledge",
         "OrderId":"CustOrd001",
         "OrderLine":[ 
            { 
               "ItemId":"ITEM533003",
               "UnitPrice":100,
               "Quantity":1
            },
            { 
               "ItemId":"ITEM533010",
               "UnitPrice":200,
               "Quantity":2
            }
         ]
      },
      { 
         "CustomerPhone":"(678) 597-7220",
         "CustomerFirstName":"Ajay",
         "CustomerEmail ":"ajay@manh.com",
         "CustomerLastName ":"Agrawal",
         "OrderId":"CustOrd002",
         "OrderLine":[ 
            { 
               "ItemId":"ITEM533003",
               "UnitPrice":100,
               "Quantity":2
            }
         ]
      }
   ]
}

